{"ApprovalTime": "2016-11-17T21:00:41Z", "AutoApprovalTime": "2016-11-17T20:59:43Z", "AssignmentId": "3QEMNNSB2XZONFB1QCGGUD2V1COD7Q", "WorkerId": "anon78", "answers": {"data": {"trial_number_block": [1, 2, 3, 4, 5, 6, 7, 8, 9, 10, 11, 12, 13, 14, 15, 16, 17, 18, 1, 2, 3, 4, 5, 1, 2, 3, 4, 5, 6, 7, 8, 9, 10, 11, 12, 13, 14, 15, 16, 17, 18], "rating": ["4", "5", "5", "0", "0", "4", "5", "2", "4", "1", "4", "0", "6", "0", "5", "4", "5", "0"], "education": ["highSchool"], "target2_rt": 32.715, "sentence": ["Children can learn about things like good and bad behavior from a very early age.", "Children should be given comfort and understanding when they are scared or unhappy.", "Holding and cradling babies is important for forming strong bonds between parent and child.", "Children don\u2019t need to learn about numbers and math until they go to school.", "Parents do not need to talk to their child about his or her emotions.", "It is important for young children to learn to control their impulses (e.g., waiting when told to wait).", "It is very important that children learn to respect adults, such as parents and teachers.", "Babies\u2019 repetitive behaviors (e.g. banging a cup on the table) are a way for them to explore cause and effect.", "Children become spoiled if they receive too much attention from parents.", "Young children should be allowed to make their own decisions, such as what to eat for dinner.", "Children should be taught to be grateful to their parents.", "Reading books to children is not helpful if they have not yet learned to speak.", "Parents need to provide safe and loving environments for their children.", "Parents should follow their children\u2019s lead rather than imposing structure in the form of rules.", "Children should not be punished for breaking small rules.", "Too much affection can make a child weak.", "Young children can teach themselves things by exploring and playing.", "It is not helpful for adults to explain the reasons for rules to young children because they won\u2019t understand.", "", "", "", "", "", "", "", "", "", "", "", "", "", "", "", "", "", "", "", "", "", "", ""], "gender": ["Woman"], "ladder": ["3"], "children": ["0"], "prior_exposure_1": ["no"], "prior_exposure_3": ["no"], "race": ["white"], "homelang": ["English"], "questionnaire_rt": 419.757, "target3_rt": 62.223, "answer": ["a", "b", "c", "c", "c", "b", "a", "a", "a", "b", "c", "a", "c", "b", "b", "a", "c", "c"], "trial_type": ["attitudes", "attitudes", "attitudes", "attitudes", "attitudes", "attitudes", "attitudes", "attitudes", "attitudes", "attitudes", "attitudes", "attitudes", "attitudes", "attitudes", "attitudes", "attitudes", "attitudes", "attitudes", "reading", "reading", "reading", "reading", "reading", "uptake", "uptake", "uptake", "uptake", "uptake", "uptake", "uptake", "uptake", "uptake", "uptake", "uptake", "uptake", "uptake", "uptake", "uptake", "uptake", "uptake", "uptake"], "target1_rt": 139.483, "age": ["20-29"], "ethnicity": ["NonHispanic"], "prior_exposure_2": ["no"]}}, "AcceptTime": "2016-11-17T20:28:05Z", "HITId": "3RQVKZ7ZRKJYXLFR3LRX9AG4SYW726", "Assignment": "", "AssignmentStatus": "Approved", "SubmitTime": "2016-11-17T20:54:43Z"}